thumbnails_readme/__init__.py
thumbnails_readme/thumbnails_readme.py
thumbnails_readme-0.4.2.dist-info/LICENSE
thumbnails_readme-0.4.2.dist-info/METADATA
thumbnails_readme-0.4.2.dist-info/WHEEL
thumbnails_readme-0.4.2.dist-info/RECORD
