Metadata-Version: 2.1
Name: thumbnails-readme
Version: 0.4.2
Summary: Create thumbnails from Git folders
Home-page: https://github.com/firefly-cpp/thumbnails-readme
Keywords: thumbnails,README
Author: Rok Kukovec
Author-email: rok.kukovec@um.si
Requires-Python: >=3.9,<4.0
Classifier: Programming Language :: Python :: 3
Classifier: Programming Language :: Python :: 3.9
Classifier: Programming Language :: Python :: 3.10
Classifier: Programming Language :: Python :: 3.11
Classifier: Programming Language :: Python :: 3.12
Requires-Dist: CairoSVG (>=2.7.1,<3.0.0)
Requires-Dist: Pillow (>=9.4,<11.0)
Requires-Dist: pdf2image (>=1.16.2,<2.0.0)
Project-URL: Repository, https://github.com/firefly-cpp/thumbnails-readme
